linguister/__init__.py
linguister/__version__.py
linguister/audio.py
linguister/config.py
linguister/const.py
linguister/errout.py
linguister/exceptions.py
linguister/info.py
linguister/main.py
linguister/utils.py
linguister/sdk/__init__.py
linguister/sdk/base.py
linguister/sdk/bing.py
linguister/sdk/google.py
linguister/sdk/iciba.py
linguister/sdk/youdao.py
tests/__init__.py
tests/_test_play.py
tests/const.py
tests/test_main.py
tests/test_out.py
tests/test_sdk.py
linguister-0.3.0.dist-info/LICENSE
linguister-0.3.0.dist-info/METADATA
linguister-0.3.0.dist-info/WHEEL
linguister-0.3.0.dist-info/entry_points.txt
linguister-0.3.0.dist-info/top_level.txt
linguister-0.3.0.dist-info/RECORD
