Metadata-Version: 2.1
Name: linguister
Version: 0.3.0
Summary: Terminal translation tool
Home-page: UNKNOWN
Author: CoCong
Author-email: cong.lv.yx@gmail.com
License: MIT
Platform: UNKNOWN
Classifier: Operating System :: Unix
Classifier: Programming Language :: Python :: 3.9
License-File: LICENSE
Requires-Dist: click
Requires-Dist: colorama
Requires-Dist: playsound
Requires-Dist: pygobject
Requires-Dist: pycairo
